guitool_ibeis/PrefWidget2.py
guitool_ibeis/PreferenceWidget.py
guitool_ibeis/__init__.py
guitool_ibeis/api_button_delegate.py
guitool_ibeis/api_item_model.py
guitool_ibeis/api_item_view.py
guitool_ibeis/api_item_widget.py
guitool_ibeis/api_table_view.py
guitool_ibeis/api_thumb_delegate.py
guitool_ibeis/api_timestamp_delegate.py
guitool_ibeis/api_tree_node.py
guitool_ibeis/api_tree_view.py
guitool_ibeis/filter_proxy_model.py
guitool_ibeis/guitool_components.py
guitool_ibeis/guitool_decorators.py
guitool_ibeis/guitool_delegates.py
guitool_ibeis/guitool_dialogs.py
guitool_ibeis/guitool_main.py
guitool_ibeis/guitool_misc.py
guitool_ibeis/guitool_tables.py
guitool_ibeis/mpl_embed.py
guitool_ibeis/mpl_widget.py
guitool_ibeis/qt_enums.py
guitool_ibeis/qtype.py
guitool_ibeis/stripe_proxy_model.py
guitool_ibeis/__PYQT__/QtCore.py
guitool_ibeis/__PYQT__/QtGui.py
guitool_ibeis/__PYQT__/QtTest.py
guitool_ibeis/__PYQT__/QtWidgets.py
guitool_ibeis/__PYQT__/__init__.py
guitool_ibeis/__PYQT__/_internal.py
guitool_ibeis/tests/__init__.py
guitool_ibeis/tests/test_treenode.py
guitool_ibeis-2.2.0.dist-info/LICENSE
guitool_ibeis-2.2.0.dist-info/METADATA
guitool_ibeis-2.2.0.dist-info/WHEEL
guitool_ibeis-2.2.0.dist-info/top_level.txt
guitool_ibeis-2.2.0.dist-info/RECORD
